{
  "best_val_precision_pos": 0.6479591836734694,
  "best_val_balanced_accuracy": 0.5958784776645768,
  "best_val_f1_macro": 0.5821669381584952,
  "best_threshold": 0.6799999999999997,
  "best_temperature": 1.5,
  "threshold_objective": "balanced_accuracy",
  "min_recall_pos": 0.75,
  "loss_name": "bce_weighted",
  "criterion_config": {
    "pos_weight": 0.4454209065679926,
    "pos_ratio": 0.69184,
    "neg_ratio": 0.30816
  },
  "sampler_strategy": "weighted",
  "normalize_features": true,
  "device": "cuda",
  "amp_enabled": true,
  "cpu_threads": 2,
  "learning_rate": 0.0003,
  "weight_decay": 0.0001,
  "scheduler_name": "plateau",
  "freeze_feature_epochs": 0,
  "batch_size": 128,
  "epochs": 40,
  "patience": 10,
  "min_epochs": 12,
  "last_checkpoint_path": "/home/bear/engagement-cpu/scripts/../checkpoints/runs/train_all_pca160_20260608_034313/rnn_tcn/engagement_tcn.last.pt",
  "resume_from": null,
  "best_objective_score": 0.5958784776645768,
  "test_loss": 0.48800573755272836,
  "test_accuracy": 0.4966367713004484,
  "test_precision_pos": 0.7639751552795031,
  "test_balanced_accuracy": 0.5595134536976217,
  "test_recall_pos": 0.3974151857835218,
  "test_recall_neg": 0.7216117216117216,
  "test_f1_macro": 0.4951132222226424,
  "prior_shift_calibration": {
    "enabled": true,
    "source_pos_prior": 0.4926522043386984,
    "target_pos_prior": 0.69184,
    "train_pos_prior": 0.69184,
    "validation_pos_prior": 0.4926522043386984,
    "test_pos_prior_observed": 0.6939461883408071
  },
  "history": [
    {
      "epoch": 1,
      "train_loss": 0.4227237794399262,
      "train_accuracy": 0.58216,
      "train_precision_pos": 0.7395612172682237,
      "train_balanced_accuracy": 0.5815522665033535,
      "train_recall_pos": 0.2512623226737196,
      "train_recall_neg": 0.9118422103329873,
      "train_f1_macro": 0.530622622270623,
      "val_loss": 0.47946813954933276,
      "val_accuracy": 0.5766270118964311,
      "val_precision_pos": 0.6083150984682714,
      "val_balanced_accuracy": 0.5739949059561129,
      "val_recall_pos": 0.39488636363636365,
      "val_recall_neg": 0.7531034482758621,
      "val_f1_macro": 0.5611930056435408,
      "val_threshold": 0.5799999999999997,
      "val_temperature": 1.5,
      "val_calibration_nll": 0.7005774470215552
    },
    {
      "epoch": 2,
      "train_loss": 0.39391957807540895,
      "train_accuracy": 0.61592,
      "train_precision_pos": 0.7967112024665981,
      "train_balanced_accuracy": 0.6156513375603958,
      "train_recall_pos": 0.310353110737449,
      "train_recall_neg": 0.9209495643833426,
      "train_f1_macro": 0.5762866565348255,
      "val_loss": 0.45640517348922827,
      "val_accuracy": 0.5837998600419874,
      "val_precision_pos": 0.6018648018648018,
      "val_balanced_accuracy": 0.5819844729623824,
      "val_recall_pos": 0.45845170454545453,
      "val_recall_neg": 0.7055172413793104,
      "val_f1_macro": 0.5764096718427845,
      "val_threshold": 0.5799999999999997,
      "val_temperature": 1.5,
      "val_calibration_nll": 0.6933404918205709
    },
    {
      "epoch": 3,
      "train_loss": 0.3774943608188629,
      "train_accuracy": 0.64236,
      "train_precision_pos": 0.8216432865731463,
      "train_balanced_accuracy": 0.6417325255571202,
      "train_recall_pos": 0.3616100064143682,
      "train_recall_neg": 0.9218550446998723,
      "train_f1_macro": 0.6115665356270018,
      "val_loss": 0.4680005989348329,
      "val_accuracy": 0.5969209237228832,
      "val_precision_pos": 0.6521997621878716,
      "val_balanced_accuracy": 0.5939177605799373,
      "val_recall_pos": 0.3895596590909091,
      "val_recall_neg": 0.7982758620689655,
      "val_f1_macro": 0.5777483002733131,
      "val_threshold": 0.6299999999999997,
      "val_temperature": 1.5,
      "val_calibration_nll": 0.6868605463690656
    },
    {
      "epoch": 4,
      "train_loss": 0.3689781543445587,
      "train_accuracy": 0.6652,
      "train_precision_pos": 0.8310170562223625,
      "train_balanced_accuracy": 0.666427825590794,
      "train_recall_pos": 0.41888234357586374,
      "train_recall_neg": 0.9139733076057244,
      "train_f1_macro": 0.6439611513276486,
      "val_loss": 0.4700060679914236,
      "val_accuracy": 0.5640307907627712,
      "val_precision_pos": 0.6025316455696202,
      "val_balanced_accuracy": 0.5607582288401254,
      "val_recall_pos": 0.3380681818181818,
      "val_recall_neg": 0.783448275862069,
      "val_f1_macro": 0.5394712542954705,
      "val_threshold": 0.6699999999999997,
      "val_temperature": 1.5,
      "val_calibration_nll": 0.7082082592245359
    },
    {
      "epoch": 5,
      "train_loss": 0.35694050706863406,
      "train_accuracy": 0.67968,
      "train_precision_pos": 0.8301608381289656,
      "train_balanced_accuracy": 0.6793690005609034,
      "train_recall_pos": 0.45069294240166624,
      "train_recall_neg": 0.9080450587201406,
      "train_f1_macro": 0.6618542547923123,
      "val_loss": 0.4696063787641852,
      "val_accuracy": 0.571553533939818,
      "val_precision_pos": 0.5997824904839587,
      "val_balanced_accuracy": 0.5689486187304075,
      "val_recall_pos": 0.3916903409090909,
      "val_recall_neg": 0.7462068965517241,
      "val_f1_macro": 0.5562648479162873,
      "val_threshold": 0.6199999999999998,
      "val_temperature": 1.5,
      "val_calibration_nll": 0.7037538223497287
    },
    {
      "epoch": 6,
      "train_loss": 0.34128197724342346,
      "train_accuracy": 0.69356,
      "train_precision_pos": 0.858104154476302,
      "train_balanced_accuracy": 0.6945971599755056,
      "train_recall_pos": 0.4671497969260174,
      "train_recall_neg": 0.922044523024994,
      "train_f1_macro": 0.6773291671650072,
      "val_loss": 0.48920883729459524,
      "val_accuracy": 0.5986703988803359,
      "val_precision_pos": 0.6479591836734694,
      "val_balanced_accuracy": 0.5958784776645768,
      "val_recall_pos": 0.40589488636363635,
      "val_recall_neg": 0.7858620689655172,
      "val_f1_macro": 0.5821669381584952,
      "val_threshold": 0.6799999999999997,
      "val_temperature": 1.5,
      "val_calibration_nll": 0.7089599251606301
    },
    {
      "epoch": 7,
      "train_loss": 0.3288139265346527,
      "train_accuracy": 0.70988,
      "train_precision_pos": 0.8686925795053003,
      "train_balanced_accuracy": 0.7093604059159381,
      "train_recall_pos": 0.4928628708901363,
      "train_recall_neg": 0.9258579409417398,
      "train_f1_macro": 0.6953764973034751,
      "val_loss": 0.5002837071392068,
      "val_accuracy": 0.5955213435969209,
      "val_precision_pos": 0.5865979381443299,
      "val_balanced_accuracy": 0.5956756955329154,
      "val_recall_pos": 0.6061789772727273,
      "val_recall_neg": 0.5851724137931035,
      "val_f1_macro": 0.5955201056201418,
      "val_threshold": 0.5099999999999998,
      "val_temperature": 1.5,
      "val_calibration_nll": 0.7060156065957703
    },
    {
      "epoch": 8,
      "train_loss": 0.3190946942615509,
      "train_accuracy": 0.72188,
      "train_precision_pos": 0.8788377192982456,
      "train_balanced_accuracy": 0.7215641087017167,
      "train_recall_pos": 0.5137408861469434,
      "train_recall_neg": 0.9293873312564901,
      "train_f1_macro": 0.7091867075058593,
      "val_loss": 0.5516147436254754,
      "val_accuracy": 0.5794261721483555,
      "val_precision_pos": 0.5746376811594203,
      "val_balanced_accuracy": 0.5791913205329153,
      "val_recall_pos": 0.5632102272727273,
      "val_recall_neg": 0.5951724137931035,
      "val_f1_macro": 0.5791737226677957,
      "val_threshold": 0.5499999999999998,
      "val_temperature": 1.5,
      "val_calibration_nll": 0.7476402240923747
    },
    {
      "epoch": 9,
      "train_loss": 0.3067189040660858,
      "train_accuracy": 0.73724,
      "train_precision_pos": 0.8901619913077835,
      "train_balanced_accuracy": 0.7371458402384016,
      "train_recall_pos": 0.540979670241716,
      "train_recall_neg": 0.9333120102350871,
      "train_f1_macro": 0.7266845262289331,
      "val_loss": 0.5935556051862916,
      "val_accuracy": 0.5955213435969209,
      "val_precision_pos": 0.5891089108910891,
      "val_balanced_accuracy": 0.5954648315047022,
      "val_recall_pos": 0.5916193181818182,
      "val_recall_neg": 0.5993103448275862,
      "val_f1_macro": 0.5954571568929485,
      "val_threshold": 0.5299999999999998,
      "val_temperature": 1.5,
      "val_calibration_nll": 0.7705015787990983
    },
    {
      "epoch": 10,
      "train_loss": 0.29902474902153015,
      "train_accuracy": 0.74492,
      "train_precision_pos": 0.8882854926299457,
      "train_balanced_accuracy": 0.7431569124798396,
      "train_recall_pos": 0.5547928611806509,
      "train_recall_neg": 0.9315209637790283,
      "train_f1_macro": 0.7348027508273135,
      "val_loss": 0.6146896998310022,
      "val_accuracy": 0.5888733379986004,
      "val_precision_pos": 0.6180344478216818,
      "val_balanced_accuracy": 0.5866193181818182,
      "val_recall_pos": 0.43323863636363635,
      "val_recall_neg": 0.74,
      "val_f1_macro": 0.57779273918928,
      "val_threshold": 0.6699999999999997,
      "val_temperature": 1.5,
      "val_calibration_nll": 0.7905986212897971
    },
    {
      "epoch": 11,
      "train_loss": 0.29170231172561645,
      "train_accuracy": 0.7532,
      "train_precision_pos": 0.8980803233139681,
      "train_balanced_accuracy": 0.7528198713998916,
      "train_recall_pos": 0.5700657367324033,
      "train_recall_neg": 0.9355740060673798,
      "train_f1_macro": 0.7445203702115648,
      "val_loss": 0.6540956644848396,
      "val_accuracy": 0.5895731280615816,
      "val_precision_pos": 0.5696502667457024,
      "val_balanced_accuracy": 0.5909193769592476,
      "val_recall_pos": 0.6825284090909091,
      "val_recall_neg": 0.4993103448275862,
      "val_f1_macro": 0.5867312541489486,
      "val_threshold": 0.45999999999999985,
      "val_temperature": 1.5,
      "val_calibration_nll": 0.8064470986596404
    },
    {
      "epoch": 12,
      "train_loss": 0.27866978533744813,
      "train_accuracy": 0.76476,
      "train_precision_pos": 0.9114247475361966,
      "train_balanced_accuracy": 0.7667680876996259,
      "train_recall_pos": 0.5924549193293261,
      "train_recall_neg": 0.9410812560699255,
      "train_f1_macro": 0.75813691055113,
      "val_loss": 0.664369074842828,
      "val_accuracy": 0.582925122463261,
      "val_precision_pos": 0.5626450116009281,
      "val_balanced_accuracy": 0.5844602272727273,
      "val_recall_pos": 0.6889204545454546,
      "val_recall_neg": 0.48,
      "val_f1_macro": 0.5790561031833584,
      "val_threshold": 0.43999999999999984,
      "val_temperature": 1.5,
      "val_calibration_nll": 0.8160799984995422
    },
    {
      "epoch": 13,
      "train_loss": 0.27128871081352235,
      "train_accuracy": 0.77636,
      "train_precision_pos": 0.9111747851002865,
      "train_balanced_accuracy": 0.7760836464184837,
      "train_recall_pos": 0.6115874669444668,
      "train_recall_neg": 0.9405798258925006,
      "train_f1_macro": 0.770038439487678,
      "val_loss": 0.7331240942129478,
      "val_accuracy": 0.5796011196641008,
      "val_precision_pos": 0.5867282654346913,
      "val_balanced_accuracy": 0.5783917025862069,
      "val_recall_pos": 0.49609375,
      "val_recall_neg": 0.6606896551724138,
      "val_f1_macro": 0.5761064422615045,
      "val_threshold": 0.6199999999999998,
      "val_temperature": 1.5,
      "val_calibration_nll": 0.8709878715758611
    },
    {
      "epoch": 14,
      "train_loss": 0.26760592875480654,
      "train_accuracy": 0.77812,
      "train_precision_pos": 0.9149487572152197,
      "train_balanced_accuracy": 0.7793159688343054,
      "train_recall_pos": 0.6168202033036849,
      "train_recall_neg": 0.9418117343649258,
      "train_f1_macro": 0.7725302265747064,
      "val_loss": 0.7448327307771185,
      "val_accuracy": 0.5705038488453464,
      "val_precision_pos": 0.5489823609226594,
      "val_balanced_accuracy": 0.5726457190438872,
      "val_recall_pos": 0.7183948863636364,
      "val_recall_neg": 0.42689655172413793,
      "val_f1_macro": 0.5622475876993294,
      "val_threshold": 0.4199999999999998,
      "val_temperature": 1.5,
      "val_calibration_nll": 0.8847645940744896
    },
    {
      "epoch": 15,
      "train_loss": 0.2610118898200989,
      "train_accuracy": 0.78532,
      "train_precision_pos": 0.9175463288763781,
      "train_balanced_accuracy": 0.7851549900236372,
      "train_recall_pos": 0.6264915512132618,
      "train_recall_neg": 0.9438184288340127,
      "train_f1_macro": 0.7797173598798134,
      "val_loss": 0.7829104709074662,
      "val_accuracy": 0.5740027991602519,
      "val_precision_pos": 0.5527554693990584,
      "val_balanced_accuracy": 0.5759551332288402,
      "val_recall_pos": 0.7088068181818182,
      "val_recall_neg": 0.44310344827586207,
      "val_f1_macro": 0.5673080614733019,
      "val_threshold": 0.4299999999999998,
      "val_temperature": 1.5,
      "val_calibration_nll": 0.9168443792881471
    },
    {
      "epoch": 16,
      "train_loss": 0.25778489649772646,
      "train_accuracy": 0.78684,
      "train_precision_pos": 0.9185842775376708,
      "train_balanced_accuracy": 0.786789610167256,
      "train_recall_pos": 0.6293213828425096,
      "train_recall_neg": 0.9442578374920025,
      "train_f1_macro": 0.7814022501639344,
      "val_loss": 0.8057417089994175,
      "val_accuracy": 0.5678796361091673,
      "val_precision_pos": 0.5572089947089947,
      "val_balanced_accuracy": 0.5683211696708463,
      "val_recall_pos": 0.5983664772727273,
      "val_recall_neg": 0.5382758620689655,
      "val_f1_macro": 0.5676761812373841,
      "val_threshold": 0.48999999999999977,
      "val_temperature": 1.5,
      "val_calibration_nll": 0.9391605151745864
    },
    {
      "epoch": 17,
      "train_loss": 0.2549258122253418,
      "train_accuracy": 0.79192,
      "train_precision_pos": 0.9229112345539054,
      "train_balanced_accuracy": 0.7938889397455366,
      "train_recall_pos": 0.6428966279712548,
      "train_recall_neg": 0.9448812515198184,
      "train_f1_macro": 0.7877212083753038,
      "val_loss": 0.7646831005832546,
      "val_accuracy": 0.5736529041287614,
      "val_precision_pos": 0.5555230002929974,
      "val_balanced_accuracy": 0.5750960031347963,
      "val_recall_pos": 0.6732954545454546,
      "val_recall_neg": 0.4768965517241379,
      "val_f1_macro": 0.5701909135433092,
      "val_threshold": 0.4199999999999998,
      "val_temperature": 1.5,
      "val_calibration_nll": 0.8991148271794691
    },
    {
      "epoch": 18,
      "train_loss": 0.25218069266319276,
      "train_accuracy": 0.7962,
      "train_precision_pos": 0.9221763085399449,
      "train_balanced_accuracy": 0.795610584070479,
      "train_recall_pos": 0.6452493775600353,
      "train_recall_neg": 0.9459717905809227,
      "train_f1_macro": 0.7912834499036225,
      "val_loss": 0.7947554250043785,
      "val_accuracy": 0.5776766969909027,
      "val_precision_pos": 0.5729847494553377,
      "val_balanced_accuracy": 0.577426038401254,
      "val_recall_pos": 0.5603693181818182,
      "val_recall_neg": 0.5944827586206897,
      "val_f1_macro": 0.5774009887496194,
      "val_threshold": 0.5099999999999998,
      "val_temperature": 1.5,
      "val_calibration_nll": 0.922476647751967
    },
    {
      "epoch": 19,
      "train_loss": 0.25069736757278444,
      "train_accuracy": 0.7974,
      "train_precision_pos": 0.9267186227753867,
      "train_balanced_accuracy": 0.7961942249557534,
      "train_recall_pos": 0.6423963876794065,
      "train_recall_neg": 0.9499920622321003,
      "train_f1_macro": 0.7920744439862502,
      "val_loss": 0.7921740588314304,
      "val_accuracy": 0.5792512246326103,
      "val_precision_pos": 0.5606731620903455,
      "val_balanced_accuracy": 0.5806286735893417,
      "val_recall_pos": 0.6743607954545454,
      "val_recall_neg": 0.4868965517241379,
      "val_f1_macro": 0.5761747002596261,
      "val_threshold": 0.4299999999999998,
      "val_temperature": 1.5,
      "val_calibration_nll": 0.9220457059599226
    },
    {
      "epoch": 20,
      "train_loss": 0.24737268746376037,
      "train_accuracy": 0.79824,
      "train_precision_pos": 0.9243668720054757,
      "train_balanced_accuracy": 0.7980493075239854,
      "train_recall_pos": 0.6490708106376162,
      "train_recall_neg": 0.9470278044103547,
      "train_f1_macro": 0.7935959079283887,
      "val_loss": 0.8517653000279688,
      "val_accuracy": 0.5799510146955913,
      "val_precision_pos": 0.5610114672155249,
      "val_balanced_accuracy": 0.5813646159874608,
      "val_recall_pos": 0.6775568181818182,
      "val_recall_neg": 0.48517241379310344,
      "val_f1_macro": 0.5766990920111883,
      "val_threshold": 0.4099999999999998,
      "val_temperature": 1.5,
      "val_calibration_nll": 0.969532205369101
    },
    {
      "epoch": 21,
      "train_loss": 0.24464886109352113,
      "train_accuracy": 0.80116,
      "train_precision_pos": 0.9284499376346524,
      "train_balanced_accuracy": 0.8014913303628992,
      "train_recall_pos": 0.6535759897828863,
      "train_recall_neg": 0.9494066709429121,
      "train_f1_macro": 0.796821934061255,
      "val_loss": 0.8454715244998625,
      "val_accuracy": 0.5797760671798461,
      "val_precision_pos": 0.5617910447761194,
      "val_balanced_accuracy": 0.5810584835423198,
      "val_recall_pos": 0.6683238636363636,
      "val_recall_neg": 0.49379310344827587,
      "val_f1_macro": 0.5771553422779983,
      "val_threshold": 0.4199999999999998,
      "val_temperature": 1.5,
      "val_calibration_nll": 0.9631287313876832
    }
  ]
}